README.txt
setup.py
collective/__init__.py
collective.pfgpreview.egg-info/PKG-INFO
collective.pfgpreview.egg-info/SOURCES.txt
collective.pfgpreview.egg-info/dependency_links.txt
collective.pfgpreview.egg-info/entry_points.txt
collective.pfgpreview.egg-info/namespace_packages.txt
collective.pfgpreview.egg-info/not-zip-safe
collective.pfgpreview.egg-info/requires.txt
collective.pfgpreview.egg-info/top_level.txt
collective/pfgpreview/__init__.py
collective/pfgpreview/configure.zcml
collective/pfgpreview/fg_confirmpage.pt
collective/pfgpreview/preview.py
collective/pfgpreview/tests.py
docs/CONTRIBUTORS.txt
docs/HISTORY.txt
docs/INSTALL.txt
docs/LICENSE.GPL
docs/LICENSE.txt