Metadata-Version: 1.0
Name: collective.pfgpreview
Version: 1.1
Summary: Preview page for PloneFormGen
Home-page: http://pypi.python.org/pypi/collective.pfgpreview
Author: Roman Kozlovskiy (kroman0)
Author-email: UNKNOWN
License: GPL
Platform: UNKNOWN
Classifier: Framework :: Plone
Classifier: Programming Language :: Python
